jrpytorch/__init__.py
jrpytorch/__version__.py
jrpytorch/datasets/__init__.py
jrpytorch/datasets/data/dogs_cats.zip
jrpytorch/datasets/data/walking.zip
jrpytorch/vignettes/practical1.pdf
jrpytorch/vignettes/practical2.pdf
jrpytorch/vignettes/practical3.pdf
jrpytorch/vignettes/practical4.pdf
jrpytorch/vignettes/solutions1.pdf
jrpytorch/vignettes/solutions2.pdf
jrpytorch/vignettes/solutions3.pdf
jrpytorch/vignettes/solutions4.pdf
jrpytorch/vignettes.py
jrpytorch/visualiser.py
jrpytorch-0.2.0.dist-info/WHEEL
jrpytorch-0.2.0.dist-info/METADATA
jrpytorch-0.2.0.dist-info/RECORD
